fastapi_listing/__init__.py
fastapi_listing/constants.py
fastapi_listing/ctyping.py
fastapi_listing/errors.py
fastapi_listing/loader.py
fastapi_listing/middlewares.py
fastapi_listing/py.typed
fastapi_listing/utils.py
fastapi_listing/abstracts/__init__.py
fastapi_listing/abstracts/adapters.py
fastapi_listing/abstracts/base_query.py
fastapi_listing/abstracts/dao.py
fastapi_listing/abstracts/filter.py
fastapi_listing/abstracts/interceptor.py
fastapi_listing/abstracts/listing.py
fastapi_listing/abstracts/paginator.py
fastapi_listing/abstracts/sorter.py
fastapi_listing/dao/__init__.py
fastapi_listing/dao/dao_registry.py
fastapi_listing/dao/generic_dao.py
fastapi_listing/factory/__init__.py
fastapi_listing/factory/_generic_factory.py
fastapi_listing/factory/filter.py
fastapi_listing/factory/interceptor.py
fastapi_listing/factory/strategy.py
fastapi_listing/filters/__init__.py
fastapi_listing/filters/generic_filters.py
fastapi_listing/interceptors/__init__.py
fastapi_listing/interceptors/individual_sorter_interceptor.py
fastapi_listing/interceptors/iterative_filter_interceptor.py
fastapi_listing/interface/__init__.py
fastapi_listing/interface/client_site_params_adapter.py
fastapi_listing/interface/listing_meta_info.py
fastapi_listing/paginator/__init__.py
fastapi_listing/paginator/default_page_format.py
fastapi_listing/paginator/page_builder.py
fastapi_listing/service/__init__.py
fastapi_listing/service/_core_listing_service.py
fastapi_listing/service/adapters.py
fastapi_listing/service/config.py
fastapi_listing/service/listing_main.py
fastapi_listing/sorter/__init__.py
fastapi_listing/sorter/page_sorter.py
fastapi_listing/strategies/__init__.py
fastapi_listing/strategies/query_strategy.py
tests/__init__.py
tests/dao_setup.py
tests/fake_listing_setup.py
tests/original_responses.py
tests/pydantic_setup.py
tests/service_setup.py
tests/test_fast_listing_compact_version.py
tests/test_main.py
tests/test_main_v2.py
fastapi_listing-0.3.4.dist-info/LICENSE
fastapi_listing-0.3.4.dist-info/METADATA
fastapi_listing-0.3.4.dist-info/WHEEL
fastapi_listing-0.3.4.dist-info/top_level.txt
fastapi_listing-0.3.4.dist-info/RECORD
