Metadata-Version: 2.2
Name: fastapi-listing
Version: 0.3.4
Summary: Advaned Data Listing Library for FastAPI
Home-page: https://github.com/danielhasan1/fastapi-listing
Author: Danish Hasan
Author-email: dh813030@gmail.com
Keywords: starlette,fastapi,pydantic,sqlalchemy
Classifier: Development Status :: 5 - Production/Stable
Classifier: Environment :: Web Environment
Classifier: Intended Audience :: Developers
Classifier: License :: OSI Approved :: MIT License
Classifier: Operating System :: OS Independent
Classifier: Programming Language :: Python
Classifier: Programming Language :: Python :: 3
Classifier: Programming Language :: Python :: 3.7
Classifier: Programming Language :: Python :: 3.8
Classifier: Programming Language :: Python :: 3.9
Classifier: Programming Language :: Python :: 3.10
Classifier: Programming Language :: Python :: 3.11
Requires-Python: >=3.7
License-File: LICENSE
Provides-Extra: test
Requires-Dist: requests; extra == "test"
Requires-Dist: pytest>=6.2.4; extra == "test"
Requires-Dist: mypy>=0.971; extra == "test"
Requires-Dist: pytest-env>=0.6.2; extra == "test"
Requires-Dist: flake8>=3.9.2; extra == "test"
Requires-Dist: isort>=5.10.1; extra == "test"
Requires-Dist: pydantic>=1.10.7; extra == "test"
Requires-Dist: starlette>=0.21.0; extra == "test"
Requires-Dist: sqlalchemy>=2.0.7; extra == "test"
Requires-Dist: starlite>=1.38.0; extra == "test"
Requires-Dist: httpx>=0.23.0; extra == "test"
Requires-Dist: pytest-mock>=3.6.1; extra == "test"
Requires-Dist: fastapi>=0.92.0; extra == "test"
Requires-Dist: mypy>=0.971; extra == "test"
Requires-Dist: pytest-mypy>=0.9.1; extra == "test"
Requires-Dist: mysqlclient; extra == "test"
Requires-Dist: pytest-cov==4.1.0; extra == "test"
Dynamic: author
Dynamic: author-email
Dynamic: classifier
Dynamic: description
Dynamic: description-content-type
Dynamic: home-page
Dynamic: keywords
Dynamic: provides-extra
Dynamic: requires-python
Dynamic: summary
